{
	"packages":{
		"maiwashi":{
			"type":"git",
			"url": "https://github.com/ubazame-club/maiwashi_public"
		},
		"urume_iwashi":{
			"type":"git",
			"url": "https://github.com/ubazame-club/RoundHerring_public"
		},
		"katakuchi_iwashi":{
			"type":"git",
			"url": "https://github.com/ubazame-club/katakuchi_iwashi_public"
		},
		"umihebi":{
			"type":"git",
			"url": "https://github.com/ubazame-club/umihebi_public"
		},
		"umihebi.tail":{
			"type":"git",
			"url": "https://github.com/ubazame-club/tail_public"
		},
		"python_runtime":{
			"type":"git",
			"url": "https://github.com/ubazame-club/python_runtime"
		}
	},
	"childs": {}
}
